README.md
setup.py
Flask_TransAlchemy.egg-info/PKG-INFO
Flask_TransAlchemy.egg-info/SOURCES.txt
Flask_TransAlchemy.egg-info/dependency_links.txt
Flask_TransAlchemy.egg-info/requires.txt
Flask_TransAlchemy.egg-info/top_level.txt
flask_transalchemy/__init__.py
flask_transalchemy/core.py
flask_transalchemy/model.py