Metadata-Version: 2.1
Name: Flask-TransAlchemy
Version: 0.1
Summary: Simple translation support for Flask-SQLAlchemy based database tables.
Home-page: https://github.com/gerelorant/Flask-TransAlchemy
Author: Gere Lóránt
Author-email: gerelorant@gmail.com
License: MIT
Platform: UNKNOWN
